conventional_commits_ronmckay_info.txt
cz_conventional_commits_ronmckay.py
cz_conventional_commits_ronmckay-0.4.0.dist-info/METADATA
cz_conventional_commits_ronmckay-0.4.0.dist-info/WHEEL
cz_conventional_commits_ronmckay-0.4.0.dist-info/RECORD
