Metadata-Version: 2.1
Name: cz-conventional-commits-ronmckay
Version: 0.4.0
Summary: 
License: MIT
Author: Philipp Oberdiek
Author-email: git@oberdiek.net
Requires-Python: >=3.7,<4.0
Classifier: License :: OSI Approved :: MIT License
Classifier: Programming Language :: Python :: 3
Classifier: Programming Language :: Python :: 3.7
Classifier: Programming Language :: Python :: 3.8
Classifier: Programming Language :: Python :: 3.9
Classifier: Programming Language :: Python :: 3.10
Classifier: Programming Language :: Python :: 3.11
Requires-Dist: commitizen (>=2.37.0,<3.0.0)
